sweref99/__init__.py
sweref99/ellipsoid.py
sweref99/ellipsoids.py
sweref99/projections.py
sweref99/transverse_mercator.py
sweref99/tests/__init__.py
sweref99/tests/test_main.py
sweref99-0.2.dist-info/LICENSE
sweref99-0.2.dist-info/METADATA
sweref99-0.2.dist-info/WHEEL
sweref99-0.2.dist-info/top_level.txt
sweref99-0.2.dist-info/RECORD
