Metadata-Version: 2.1
Name: sweref99
Version: 0.2
Summary: A SWEREF 99 map projection library
Home-page: UNKNOWN
Author: Kasper Ingelvide
Author-email: kasper.ingelvide@layer10.se
License: UNKNOWN
Platform: UNKNOWN
Classifier: Programming Language :: Python :: 3
Classifier: License :: OSI Approved :: MIT License
Classifier: Operating System :: OS Independent
Requires-Python: >=3.6
